easyprotocol/__init__.py
easyprotocol/base/__init__.py
easyprotocol/base/parse_base.py
easyprotocol/base/parse_field_dict.py
easyprotocol/base/parse_field_list.py
easyprotocol/base/parse_generic_dict.py
easyprotocol/base/parse_generic_list.py
easyprotocol/base/parse_generic_value.py
easyprotocol/base/parse_value_list.py
easyprotocol/base/utils.py
easyprotocol/fields/__init__.py
easyprotocol/fields/array.py
easyprotocol/fields/checksum.py
easyprotocol/fields/enum.py
easyprotocol/fields/flags.py
easyprotocol/fields/float.py
easyprotocol/fields/signed_int.py
easyprotocol/fields/string.py
easyprotocol/fields/unsigned_int.py
easyprotocol/protocols/__init__.py
easyprotocol/protocols/modbus/__init__.py
easyprotocol/protocols/modbus/constants.py
easyprotocol/protocols/modbus/fields.py
easyprotocol/protocols/modbus/frames.py
easyprotocol/protocols/modbus/modbus_client.py
easyprotocol/protocols/modbus/modbus_server.py
easyprotocol/protocols/modbus/modbus_transceiver.py
easyprotocol/py.typed
easyprotocol-0.0.3.dist-info/LICENSE
easyprotocol-0.0.3.dist-info/WHEEL
easyprotocol-0.0.3.dist-info/METADATA
easyprotocol-0.0.3.dist-info/RECORD
