Metadata-Version: 2.1
Name: easyprotocol
Version: 0.0.3
Summary: A library for quick protocol prototyping and parsing.
License: MIT
Author: joeferg425
Requires-Python: >=3.8,<4.0
Classifier: License :: OSI Approved :: MIT License
Classifier: Programming Language :: Python :: 3
Classifier: Programming Language :: Python :: 3.10
Classifier: Programming Language :: Python :: 3.8
Classifier: Programming Language :: Python :: 3.9
Requires-Dist: bitarray (>=2.6.0,<3.0.0)
Requires-Dist: crc (>=2.0.0,<3.0.0)
